{
 "custom_fields": [], 
 "doctype": "Payment Entry", 
 "property_setters": [
  {
   "_assign": null, 
   "_comments": null, 
   "_liked_by": null, 
   "_user_tags": null, 
   "creation": "2017-01-10 15:57:00.110417", 
   "default_value": null, 
   "doc_type": "Payment Entry", 
   "docstatus": 0, 
   "doctype_or_field": "DocField", 
   "field_name": "mode_of_payment", 
   "idx": 0, 
   "modified": "2017-01-10 15:57:00.110417", 
   "modified_by": "Administrator", 
   "name": "Payment Entry-mode_of_payment-remember_last_selected_value", 
   "owner": "Administrator", 
   "parent": null, 
   "parentfield": null, 
   "parenttype": null, 
   "property": "remember_last_selected_value", 
   "property_type": "Check", 
   "value": "1"
  }, 
  {
   "_assign": null, 
   "_comments": null, 
   "_liked_by": null, 
   "_user_tags": null, 
   "creation": "2017-01-10 15:57:00.104664", 
   "default_value": null, 
   "doc_type": "Payment Entry", 
   "docstatus": 0, 
   "doctype_or_field": "DocField", 
   "field_name": "mode_of_payment", 
   "idx": 0, 
   "modified": "2017-01-10 15:57:00.104664", 
   "modified_by": "Administrator", 
   "name": "Payment Entry-mode_of_payment-reqd", 
   "owner": "Administrator", 
   "parent": null, 
   "parentfield": null, 
   "parenttype": null, 
   "property": "reqd", 
   "property_type": "Check", 
   "value": "1"
  }, 
  {
   "_assign": null, 
   "_comments": null, 
   "_liked_by": null, 
   "_user_tags": null, 
   "creation": "2017-01-10 15:57:00.067509", 
   "default_value": null, 
   "doc_type": "Payment Entry", 
   "docstatus": 0, 
   "doctype_or_field": "DocType", 
   "field_name": null, 
   "idx": 0, 
   "modified": "2017-01-10 15:57:00.067509", 
   "modified_by": "Administrator", 
   "name": "Payment Entry-read_only_onload", 
   "owner": "Administrator", 
   "parent": null, 
   "parentfield": null, 
   "parenttype": null, 
   "property": "read_only_onload", 
   "property_type": "Check", 
   "value": null
  }, 
  {
   "_assign": null, 
   "_comments": null, 
   "_liked_by": null, 
   "_user_tags": null, 
   "creation": "2017-01-10 15:53:57.981259", 
   "default_value": null, 
   "doc_type": "Payment Entry", 
   "docstatus": 0, 
   "doctype_or_field": "DocType", 
   "field_name": null, 
   "idx": 0, 
   "modified": "2017-01-10 15:53:57.981259", 
   "modified_by": "Administrator", 
   "name": "Payment Entry-quick_entry", 
   "owner": "Administrator", 
   "parent": null, 
   "parentfield": null, 
   "parenttype": null, 
   "property": "quick_entry", 
   "property_type": "Check", 
   "value": "1"
  }, 
  {
   "_assign": null, 
   "_comments": null, 
   "_liked_by": null, 
   "_user_tags": null, 
   "creation": "2017-01-10 15:28:15.951311", 
   "default_value": null, 
   "doc_type": "Payment Entry", 
   "docstatus": 0, 
   "doctype_or_field": "DocField", 
   "field_name": "reference_no", 
   "idx": 0, 
   "modified": "2017-01-10 15:28:15.951311", 
   "modified_by": "Administrator", 
   "name": "Payment Entry-reference_no-description", 
   "owner": "Administrator", 
   "parent": null, 
   "parentfield": null, 
   "parenttype": null, 
   "property": "description", 
   "property_type": "Text", 
   "value": "Referen\u010dna \u0161tevilka pla\u010dila"
  }, 
  {
   "_assign": null, 
   "_comments": null, 
   "_liked_by": null, 
   "_user_tags": null, 
   "creation": "2017-01-10 15:28:15.948258", 
   "default_value": null, 
   "doc_type": "Payment Entry", 
   "docstatus": 0, 
   "doctype_or_field": "DocField", 
   "field_name": "reference_no", 
   "idx": 0, 
   "modified": "2017-01-10 15:28:15.948258", 
   "modified_by": "Administrator", 
   "name": "Payment Entry-reference_no-reqd", 
   "owner": "Administrator", 
   "parent": null, 
   "parentfield": null, 
   "parenttype": null, 
   "property": "reqd", 
   "property_type": "Check", 
   "value": "1"
  }, 
  {
   "_assign": null, 
   "_comments": null, 
   "_liked_by": null, 
   "_user_tags": null, 
   "creation": "2016-09-04 11:07:00.756267", 
   "default_value": null, 
   "doc_type": "Payment Entry", 
   "docstatus": 0, 
   "doctype_or_field": "DocField", 
   "field_name": "naming_series", 
   "idx": 0, 
   "modified": "2016-09-04 11:07:00.756267", 
   "modified_by": "Administrator", 
   "name": "Payment Entry-naming_series-options", 
   "owner": "Administrator", 
   "parent": null, 
   "parentfield": null, 
   "parenttype": null, 
   "property": "options", 
   "property_type": "Text", 
   "value": "PE-"
  }
 ], 
 "sync_on_migrate": 1
}